statsd_ostools
