Metadata-Version: 1.0
Name: statsd-ostools
Version: 0.2
Summary: Tools for sending OS performance data to statsd
Home-page: https://github.com/dlamotte/statsd-ostools
Author: Dan LaMotte
Author-email: lamotte85@gmail.com
License: UNKNOWN
Platform: UNKNOWN
